

{
  "description": "Description ", 
  "external_url": "", 
  "image": "https://storage.googleapis.com/opensea-prod.appspot.com/puffs/3.png", 
  "name": "Excellence Award",
  "attributes": [ 
    {
        "issued_by_group": "Issued By Group", 
        "value": "Starfish"
      }, 
      {
        "issued_by_user": "Issued By User", 
        "value": "Big"
      }, 
      {
        "issued_to_group": "Issued To User", 
        "value": "Starfish"
      }, 
      {
        "issued_to_user": "Issued To Group",
        "value": "Big"
      }
   ]
}